{
  "imageId": "topup-txmoney-page",
  "annotations": [
    {
      "id": "balance",
      "type": "box",
      "number": 1,
      "x": 3,
      "y": 4,
      "width": 54,
      "height": 52
    },
    {
      "id": "amount-input",
      "type": "box",
      "number": 2,
      "x": 3,
      "y": 60,
      "width": 95,
      "height": 22
    },
    {
      "id": "btn-bank",
      "type": "marker",
      "number": 3,
      "x": 10,
      "y": 92
    },
    {
      "id": "btn-card",
      "type": "marker",
      "number": 4,
      "x": 29,
      "y": 92
    }
  ]
}
