{
  "imageId": "waybills-print-barcode-label-01",
  "annotations": [
    {
      "id": "marker-1776071866321-1",
      "type": "marker",
      "number": 1,
      "x": 3.273809523809524,
      "y": 15.262515262515263
    },
    {
      "id": "marker-1776071868334-2",
      "type": "marker",
      "number": 2,
      "x": 2.6785714285714284,
      "y": 39.56043956043956
    },
    {
      "id": "marker-1776071870092-3",
      "type": "marker",
      "number": 3,
      "x": 2.976190476190476,
      "y": 72.28327228327228
    },
    {
      "id": "marker-1776071871781-4",
      "type": "marker",
      "number": 4,
      "x": 8.630952380952381,
      "y": 80.58608058608058
    },
    {
      "id": "marker-1776071872980-5",
      "type": "marker",
      "number": 5,
      "x": 86.30952380952381,
      "y": 89.49938949938951
    }
  ]
}